github/__init__.py
github/io/__init__.py
github/io/game1.py
qiye_game1-0.1.2.dist-info/METADATA
qiye_game1-0.1.2.dist-info/WHEEL
qiye_game1-0.1.2.dist-info/top_level.txt
qiye_game1-0.1.2.dist-info/RECORD
