Metadata-Version: 2.1
Name: qiye-game1
Version: 0.1.2
Summary: 孤独终老 --邓海林
Home-page: UNKNOWN
Author: qiye
Author-email: UNKNOWN
License: UNKNOWN
Platform: UNKNOWN
